{"words":[
{"senses": [{"links": [["kyberpunk", "kyberpunk#Finnish"]], "glosses": ["Alternative spelling of kyberpunk"], "tags": ["alt-of", "alternative"], "alt_of": [{"word": "kyberpunk"}], "categories": ["Finnish 3-syllable words", "Finnish lemmas", "Finnish nouns", "Finnish risti-type nominals", "Finnish terms spelled with C", "Finnish terms with IPA pronunciation", "Finnish uncountable nouns", "fi-pronunciation missing hyphenation or rhymes"]}], "pos": "noun", "head_templates": [{"name": "head", "args": {"1": "fi", "2": "nouns", "head": "", "sort": "", "g": "", "cat2": ""}, "expansion": "cyberpunk"}, {"name": "fi-noun", "args": {}, "expansion": "cyberpunk"}], "inflection_templates": [{"name": "fi-decl-risti", "args": {"i": "0", "nopl": "1", "1": "cyberpunk", "2": "", "3": "", "4": "a"}}], "forms": [{"form": "", "source": "declension", "tags": ["table-tags"]}, {"form": "fi-decl-risti", "source": "declension", "tags": ["inflection-template"]}, {"form": "no gradation", "source": "declension", "tags": ["class"]}, {"form": "5/risti", "source": "declension", "tags": ["class"]}, {"form": "cyberpunk", "tags": ["nominative", "singular"], "source": "declension"}, {"form": "-", "tags": ["nominative", "plural"], "source": "declension"}, {"form": "cyberpunk", "tags": ["accusative", "nominative", "singular"], "source": "declension"}, {"form": "-", "tags": ["accusative", "nominative", "plural"], "source": "declension"}, {"form": "cyberpunkin", "tags": ["accusative", "genitive", "singular"], "source": "declension"}, {"form": "-", "tags": ["accusative", "genitive", "plural"], "source": "declension"}, {"form": "cyberpunkin", "tags": ["genitive", "singular"], "source": "declension"}, {"form": "-", "tags": ["genitive", "plural"], "source": "declension"}, {"form": "cyberpunkia", "tags": ["partitive", "singular"], "source": "declension"}, {"form": "-", "tags": ["partitive", "plural"], "source": "declension"}, {"form": "cyberpunkissa", "tags": ["inessive", "singular"], "source": "declension"}, {"form": "-", "tags": ["inessive", "plural"], "source": "declension"}, {"form": "cyberpunkista", "tags": ["elative", "singular"], "source": "declension"}, {"form": "-", "tags": ["elative", "plural"], "source": "declension"}, {"form": "cyberpunkiin", "tags": ["illative", "singular"], "source": "declension"}, {"form": "-", "tags": ["illative", "plural"], "source": "declension"}, {"form": "cyberpunkilla", "tags": ["adessive", "singular"], "source": "declension"}, {"form": "-", "tags": ["adessive", "plural"], "source": "declension"}, {"form": "cyberpunkilta", "tags": ["ablative", "singular"], "source": "declension"}, {"form": "-", "tags": ["ablative", "plural"], "source": "declension"}, {"form": "cyberpunkille", "tags": ["allative", "singular"], "source": "declension"}, {"form": "-", "tags": ["allative", "plural"], "source": "declension"}, {"form": "cyberpunkina", "tags": ["essive", "singular"], "source": "declension"}, {"form": "-", "tags": ["essive", "plural"], "source": "declension"}, {"form": "cyberpunkiksi", "tags": ["singular", "translative"], "source": "declension"}, {"form": "-", "tags": ["plural", "translative"], "source": "declension"}, {"form": "-", "tags": ["instructive", "singular"], "source": "declension"}, {"form": "-", "tags": ["instructive", "plural"], "source": "declension"}, {"form": "cyberpunkitta", "tags": ["abessive", "singular"], "source": "declension"}, {"form": "-", "tags": ["abessive", "plural"], "source": "declension"}, {"form": "See the possessive forms below.", "tags": ["comitative"], "source": "declension"}, {"form": "", "source": "declension", "tags": ["table-tags"]}, {"form": "fi-decl-risti", "source": "declension", "tags": ["inflection-template"]}, {"form": "risti", "source": "declension", "tags": ["class"]}, {"form": "", "source": "declension", "tags": ["table-tags"]}, {"form": "fi-decl-risti", "source": "declension", "tags": ["inflection-template"]}, {"form": "cyberpunkini", "tags": ["nominative", "singular"], "source": "declension"}, {"form": "-", "tags": ["nominative", "plural"], "source": "declension"}, {"form": "cyberpunkini", "tags": ["accusative", "nominative", "singular"], "source": "declension"}, {"form": "-", "tags": ["accusative", "nominative", "plural"], "source": "declension"}, {"form": "cyberpunkini", "tags": ["accusative", "genitive", "singular"], "source": "declension"}, {"form": "-", "tags": ["accusative", "genitive", "plural"], "source": "declension"}, {"form": "cyberpunkini", "tags": ["genitive", "singular"], "source": "declension"}, {"form": "-", "tags": ["genitive", "plural"], "source": "declension"}, {"form": "cyberpunkiani", "tags": ["partitive", "singular"], "source": "declension"}, {"form": "-", "tags": ["partitive", "plural"], "source": "declension"}, {"form": "cyberpunkissani", "tags": ["inessive", "singular"], "source": "declension"}, {"form": "-", "tags": ["inessive", "plural"], "source": "declension"}, {"form": "cyberpunkistani", "tags": ["elative", "singular"], "source": "declension"}, {"form": "-", "tags": ["elative", "plural"], "source": "declension"}, {"form": "cyberpunkiini", "tags": ["illative", "singular"], "source": "declension"}, {"form": "-", "tags": ["illative", "plural"], "source": "declension"}, {"form": "cyberpunkillani", "tags": ["adessive", "singular"], "source": "declension"}, {"form": "-", "tags": ["adessive", "plural"], "source": "declension"}, {"form": "cyberpunkiltani", "tags": ["ablative", "singular"], "source": "declension"}, {"form": "-", "tags": ["ablative", "plural"], "source": "declension"}, {"form": "cyberpunkilleni", "tags": ["allative", "singular"], "source": "declension"}, {"form": "-", "tags": ["allative", "plural"], "source": "declension"}, {"form": "cyberpunkinani", "tags": ["essive", "singular"], "source": "declension"}, {"form": "-", "tags": ["essive", "plural"], "source": "declension"}, {"form": "cyberpunkikseni", "tags": ["singular", "translative"], "source": "declension"}, {"form": "-", "tags": ["plural", "translative"], "source": "declension"}, {"form": "-", "tags": ["instructive", "singular"], "source": "declension"}, {"form": "-", "tags": ["instructive", "plural"], "source": "declension"}, {"form": "cyberpunkittani", "tags": ["abessive", "singular"], "source": "declension"}, {"form": "-", "tags": ["abessive", "plural"], "source": "declension"}, {"form": "-", "tags": ["comitative", "singular"], "source": "declension"}, {"form": "-", "tags": ["comitative", "plural"], "source": "declension"}, {"form": "", "source": "declension", "tags": ["table-tags"]}, {"form": "fi-decl-risti", "source": "declension", "tags": ["inflection-template"]}, {"form": "cyberpunkisi", "tags": ["nominative", "singular"], "source": "declension"}, {"form": "-", "tags": ["nominative", "plural"], "source": "declension"}, {"form": "cyberpunkisi", "tags": ["accusative", "nominative", "singular"], "source": "declension"}, {"form": "-", "tags": ["accusative", "nominative", "plural"], "source": "declension"}, {"form": "cyberpunkisi", "tags": ["accusative", "genitive", "singular"], "source": "declension"}, {"form": "-", "tags": ["accusative", "genitive", "plural"], "source": "declension"}, {"form": "cyberpunkisi", "tags": ["genitive", "singular"], "source": "declension"}, {"form": "-", "tags": ["genitive", "plural"], "source": "declension"}, {"form": "cyberpunkiasi", "tags": ["partitive", "singular"], "source": "declension"}, {"form": "-", "tags": ["partitive", "plural"], "source": "declension"}, {"form": "cyberpunkissasi", "tags": ["inessive", "singular"], "source": "declension"}, {"form": "-", "tags": ["inessive", "plural"], "source": "declension"}, {"form": "cyberpunkistasi", "tags": ["elative", "singular"], "source": "declension"}, {"form": "-", "tags": ["elative", "plural"], "source": "declension"}, {"form": "cyberpunkiisi", "tags": ["illative", "singular"], "source": "declension"}, {"form": "-", "tags": ["illative", "plural"], "source": "declension"}, {"form": "cyberpunkillasi", "tags": ["adessive", "singular"], "source": "declension"}, {"form": "-", "tags": ["adessive", "plural"], "source": "declension"}, {"form": "cyberpunkiltasi", "tags": ["ablative", "singular"], "source": "declension"}, {"form": "-", "tags": ["ablative", "plural"], "source": "declension"}, {"form": "cyberpunkillesi", "tags": ["allative", "singular"], "source": "declension"}, {"form": "-", "tags": ["allative", "plural"], "source": "declension"}, {"form": "cyberpunkinasi", "tags": ["essive", "singular"], "source": "declension"}, {"form": "-", "tags": ["essive", "plural"], "source": "declension"}, {"form": "cyberpunkiksesi", "tags": ["singular", "translative"], "source": "declension"}, {"form": "-", "tags": ["plural", "translative"], "source": "declension"}, {"form": "-", "tags": ["instructive", "singular"], "source": "declension"}, {"form": "-", "tags": ["instructive", "plural"], "source": "declension"}, {"form": "cyberpunkittasi", "tags": ["abessive", "singular"], "source": "declension"}, {"form": "-", "tags": ["abessive", "plural"], "source": "declension"}, {"form": "-", "tags": ["comitative", "singular"], "source": "declension"}, {"form": "-", "tags": ["comitative", "plural"], "source": "declension"}, {"form": "", "source": "declension", "tags": ["table-tags"]}, {"form": "fi-decl-risti", "source": "declension", "tags": ["inflection-template"]}, {"form": "cyberpunkimme", "tags": ["nominative", "singular"], "source": "declension"}, {"form": "-", "tags": ["nominative", "plural"], "source": "declension"}, {"form": "cyberpunkimme", "tags": ["accusative", "nominative", "singular"], "source": "declension"}, {"form": "-", "tags": ["accusative", "nominative", "plural"], "source": "declension"}, {"form": "cyberpunkimme", "tags": ["accusative", "genitive", "singular"], "source": "declension"}, {"form": "-", "tags": ["accusative", "genitive", "plural"], "source": "declension"}, {"form": "cyberpunkimme", "tags": ["genitive", "singular"], "source": "declension"}, {"form": "-", "tags": ["genitive", "plural"], "source": "declension"}, {"form": "cyberpunkiamme", "tags": ["partitive", "singular"], "source": "declension"}, {"form": "-", "tags": ["partitive", "plural"], "source": "declension"}, {"form": "cyberpunkissamme", "tags": ["inessive", "singular"], "source": "declension"}, {"form": "-", "tags": ["inessive", "plural"], "source": "declension"}, {"form": "cyberpunkistamme", "tags": ["elative", "singular"], "source": "declension"}, {"form": "-", "tags": ["elative", "plural"], "source": "declension"}, {"form": "cyberpunkiimme", "tags": ["illative", "singular"], "source": "declension"}, {"form": "-", "tags": ["illative", "plural"], "source": "declension"}, {"form": "cyberpunkillamme", "tags": ["adessive", "singular"], "source": "declension"}, {"form": "-", "tags": ["adessive", "plural"], "source": "declension"}, {"form": "cyberpunkiltamme", "tags": ["ablative", "singular"], "source": "declension"}, {"form": "-", "tags": ["ablative", "plural"], "source": "declension"}, {"form": "cyberpunkillemme", "tags": ["allative", "singular"], "source": "declension"}, {"form": "-", "tags": ["allative", "plural"], "source": "declension"}, {"form": "cyberpunkinamme", "tags": ["essive", "singular"], "source": "declension"}, {"form": "-", "tags": ["essive", "plural"], "source": "declension"}, {"form": "cyberpunkiksemme", "tags": ["singular", "translative"], "source": "declension"}, {"form": "-", "tags": ["plural", "translative"], "source": "declension"}, {"form": "-", "tags": ["instructive", "singular"], "source": "declension"}, {"form": "-", "tags": ["instructive", "plural"], "source": "declension"}, {"form": "cyberpunkittamme", "tags": ["abessive", "singular"], "source": "declension"}, {"form": "-", "tags": ["abessive", "plural"], "source": "declension"}, {"form": "-", "tags": ["comitative", "singular"], "source": "declension"}, {"form": "-", "tags": ["comitative", "plural"], "source": "declension"}, {"form": "", "source": "declension", "tags": ["table-tags"]}, {"form": "fi-decl-risti", "source": "declension", "tags": ["inflection-template"]}, {"form": "cyberpunkinne", "tags": ["nominative", "singular"], "source": "declension"}, {"form": "-", "tags": ["nominative", "plural"], "source": "declension"}, {"form": "cyberpunkinne", "tags": ["accusative", "nominative", "singular"], "source": "declension"}, {"form": "-", "tags": ["accusative", "nominative", "plural"], "source": "declension"}, {"form": "cyberpunkinne", "tags": ["accusative", "genitive", "singular"], "source": "declension"}, {"form": "-", "tags": ["accusative", "genitive", "plural"], "source": "declension"}, {"form": "cyberpunkinne", "tags": ["genitive", "singular"], "source": "declension"}, {"form": "-", "tags": ["genitive", "plural"], "source": "declension"}, {"form": "cyberpunkianne", "tags": ["partitive", "singular"], "source": "declension"}, {"form": "-", "tags": ["partitive", "plural"], "source": "declension"}, {"form": "cyberpunkissanne", "tags": ["inessive", "singular"], "source": "declension"}, {"form": "-", "tags": ["inessive", "plural"], "source": "declension"}, {"form": "cyberpunkistanne", "tags": ["elative", "singular"], "source": "declension"}, {"form": "-", "tags": ["elative", "plural"], "source": "declension"}, {"form": "cyberpunkiinne", "tags": ["illative", "singular"], "source": "declension"}, {"form": "-", "tags": ["illative", "plural"], "source": "declension"}, {"form": "cyberpunkillanne", "tags": ["adessive", "singular"], "source": "declension"}, {"form": "-", "tags": ["adessive", "plural"], "source": "declension"}, {"form": "cyberpunkiltanne", "tags": ["ablative", "singular"], "source": "declension"}, {"form": "-", "tags": ["ablative", "plural"], "source": "declension"}, {"form": "cyberpunkillenne", "tags": ["allative", "singular"], "source": "declension"}, {"form": "-", "tags": ["allative", "plural"], "source": "declension"}, {"form": "cyberpunkinanne", "tags": ["essive", "singular"], "source": "declension"}, {"form": "-", "tags": ["essive", "plural"], "source": "declension"}, {"form": "cyberpunkiksenne", "tags": ["singular", "translative"], "source": "declension"}, {"form": "-", "tags": ["plural", "translative"], "source": "declension"}, {"form": "-", "tags": ["instructive", "singular"], "source": "declension"}, {"form": "-", "tags": ["instructive", "plural"], "source": "declension"}, {"form": "cyberpunkittanne", "tags": ["abessive", "singular"], "source": "declension"}, {"form": "-", "tags": ["abessive", "plural"], "source": "declension"}, {"form": "-", "tags": ["comitative", "singular"], "source": "declension"}, {"form": "-", "tags": ["comitative", "plural"], "source": "declension"}, {"form": "", "source": "declension", "tags": ["table-tags"]}, {"form": "fi-decl-risti", "source": "declension", "tags": ["inflection-template"]}, {"form": "cyberpunkinsa", "tags": ["nominative", "singular"], "source": "declension"}, {"form": "-", "tags": ["nominative", "plural"], "source": "declension"}, {"form": "cyberpunkinsa", "tags": ["accusative", "nominative", "singular"], "source": "declension"}, {"form": "-", "tags": ["accusative", "nominative", "plural"], "source": "declension"}, {"form": "cyberpunkinsa", "tags": ["accusative", "genitive", "singular"], "source": "declension"}, {"form": "-", "tags": ["accusative", "genitive", "plural"], "source": "declension"}, {"form": "cyberpunkinsa", "tags": ["genitive", "singular"], "source": "declension"}, {"form": "-", "tags": ["genitive", "plural"], "source": "declension"}, {"form": "cyberpunkiaan", "tags": ["partitive", "singular"], "source": "declension"}, {"form": "cyberpunkiansa", "tags": ["partitive", "singular"], "source": "declension"}, {"form": "-", "tags": ["partitive", "plural"], "source": "declension"}, {"form": "cyberpunkissaan", "tags": ["inessive", "singular"], "source": "declension"}, {"form": "cyberpunkissansa", "tags": ["inessive", "singular"], "source": "declension"}, {"form": "-", "tags": ["inessive", "plural"], "source": "declension"}, {"form": "cyberpunkistaan", "tags": ["elative", "singular"], "source": "declension"}, {"form": "cyberpunkistansa", "tags": ["elative", "singular"], "source": "declension"}, {"form": "-", "tags": ["elative", "plural"], "source": "declension"}, {"form": "cyberpunkiinsa", "tags": ["illative", "singular"], "source": "declension"}, {"form": "-", "tags": ["illative", "plural"], "source": "declension"}, {"form": "cyberpunkillaan", "tags": ["adessive", "singular"], "source": "declension"}, {"form": "cyberpunkillansa", "tags": ["adessive", "singular"], "source": "declension"}, {"form": "-", "tags": ["adessive", "plural"], "source": "declension"}, {"form": "cyberpunkiltaan", "tags": ["ablative", "singular"], "source": "declension"}, {"form": "cyberpunkiltansa", "tags": ["ablative", "singular"], "source": "declension"}, {"form": "-", "tags": ["ablative", "plural"], "source": "declension"}, {"form": "cyberpunkilleen", "tags": ["allative", "singular"], "source": "declension"}, {"form": "cyberpunkillensa", "tags": ["allative", "singular"], "source": "declension"}, {"form": "-", "tags": ["allative", "plural"], "source": "declension"}, {"form": "cyberpunkinaan", "tags": ["essive", "singular"], "source": "declension"}, {"form": "cyberpunkinansa", "tags": ["essive", "singular"], "source": "declension"}, {"form": "-", "tags": ["essive", "plural"], "source": "declension"}, {"form": "cyberpunkikseen", "tags": ["singular", "translative"], "source": "declension"}, {"form": "cyberpunkiksensa", "tags": ["singular", "translative"], "source": "declension"}, {"form": "-", "tags": ["plural", "translative"], "source": "declension"}, {"form": "-", "tags": ["instructive", "singular"], "source": "declension"}, {"form": "-", "tags": ["instructive", "plural"], "source": "declension"}, {"form": "cyberpunkittaan", "tags": ["abessive", "singular"], "source": "declension"}, {"form": "cyberpunkittansa", "tags": ["abessive", "singular"], "source": "declension"}, {"form": "-", "tags": ["abessive", "plural"], "source": "declension"}, {"form": "-", "tags": ["comitative", "singular"], "source": "declension"}, {"form": "-", "tags": ["comitative", "plural"], "source": "declension"}], "word": "cyberpunk", "lang": "Finnish", "lang_code": "fi", "sounds": [{"ipa": "/ˈsɑi̯berpuŋk/"}, {"ipa": "[ˈs̠ɑ̝i̯be̞rpuŋk]"}]}
]}
