{"words":[
{"senses": [{"links": [["Lhasa apso", "Lhasa apso"]], "glosses": ["Lhasa apso (breed of dog)"], "categories": ["Finnish lemmas", "Finnish multiword terms", "Finnish nouns", "Finnish valo-type nominals"]}], "pos": "noun", "head_templates": [{"name": "head", "args": {"1": "fi", "2": "nouns", "head": "", "sort": "", "g": "", "cat2": ""}, "expansion": "lhasa apso"}, {"name": "fi-noun", "args": {}, "expansion": "lhasa apso"}], "inflection_templates": [{"name": "fi-decl-valo", "args": {"1": "lhasa aps", "2": "", "3": "", "4": "o", "5": "a"}}], "forms": [{"form": "", "source": "declension", "tags": ["table-tags"]}, {"form": "fi-decl-valo", "source": "declension", "tags": ["inflection-template"]}, {"form": "no gradation", "source": "declension", "tags": ["class"]}, {"form": "1/valo", "source": "declension", "tags": ["class"]}, {"form": "lhasa apso", "tags": ["nominative", "singular"], "source": "declension"}, {"form": "lhasa apsot", "tags": ["nominative", "plural"], "source": "declension"}, {"form": "lhasa apso", "tags": ["accusative", "nominative", "singular"], "source": "declension"}, {"form": "lhasa apsot", "tags": ["accusative", "nominative", "plural"], "source": "declension"}, {"form": "lhasa apson", "tags": ["accusative", "genitive", "singular"], "source": "declension"}, {"form": "lhasa apsot", "tags": ["accusative", "genitive", "plural"], "source": "declension"}, {"form": "lhasa apson", "tags": ["genitive", "singular"], "source": "declension"}, {"form": "lhasa apsojen", "tags": ["genitive", "plural"], "source": "declension"}, {"form": "lhasa apsoa", "tags": ["partitive", "singular"], "source": "declension"}, {"form": "lhasa apsoja", "tags": ["partitive", "plural"], "source": "declension"}, {"form": "lhasa apsossa", "tags": ["inessive", "singular"], "source": "declension"}, {"form": "lhasa apsoissa", "tags": ["inessive", "plural"], "source": "declension"}, {"form": "lhasa apsosta", "tags": ["elative", "singular"], "source": "declension"}, {"form": "lhasa apsoista", "tags": ["elative", "plural"], "source": "declension"}, {"form": "lhasa apsoon", "tags": ["illative", "singular"], "source": "declension"}, {"form": "lhasa apsoihin", "tags": ["illative", "plural"], "source": "declension"}, {"form": "lhasa apsolla", "tags": ["adessive", "singular"], "source": "declension"}, {"form": "lhasa apsoilla", "tags": ["adessive", "plural"], "source": "declension"}, {"form": "lhasa apsolta", "tags": ["ablative", "singular"], "source": "declension"}, {"form": "lhasa apsoilta", "tags": ["ablative", "plural"], "source": "declension"}, {"form": "lhasa apsolle", "tags": ["allative", "singular"], "source": "declension"}, {"form": "lhasa apsoille", "tags": ["allative", "plural"], "source": "declension"}, {"form": "lhasa apsona", "tags": ["essive", "singular"], "source": "declension"}, {"form": "lhasa apsoina", "tags": ["essive", "plural"], "source": "declension"}, {"form": "lhasa apsoksi", "tags": ["singular", "translative"], "source": "declension"}, {"form": "lhasa apsoiksi", "tags": ["plural", "translative"], "source": "declension"}, {"form": "-", "tags": ["instructive", "singular"], "source": "declension"}, {"form": "lhasa apsoin", "tags": ["instructive", "plural"], "source": "declension"}, {"form": "lhasa apsotta", "tags": ["abessive", "singular"], "source": "declension"}, {"form": "lhasa apsoitta", "tags": ["abessive", "plural"], "source": "declension"}, {"form": "See the possessive forms below.", "tags": ["comitative"], "source": "declension"}, {"form": "", "source": "declension", "tags": ["table-tags"]}, {"form": "fi-decl-valo", "source": "declension", "tags": ["inflection-template"]}, {"form": "valo", "source": "declension", "tags": ["class"]}, {"form": "", "source": "declension", "tags": ["table-tags"]}, {"form": "fi-decl-valo", "source": "declension", "tags": ["inflection-template"]}, {"form": "lhasa apsoni", "tags": ["nominative", "singular"], "source": "declension"}, {"form": "lhasa apsoni", "tags": ["nominative", "plural"], "source": "declension"}, {"form": "lhasa apsoni", "tags": ["accusative", "nominative", "singular"], "source": "declension"}, {"form": "lhasa apsoni", "tags": ["accusative", "nominative", "plural"], "source": "declension"}, {"form": "lhasa apsoni", "tags": ["accusative", "genitive", "singular"], "source": "declension"}, {"form": "lhasa apsoni", "tags": ["accusative", "genitive", "plural"], "source": "declension"}, {"form": "lhasa apsoni", "tags": ["genitive", "singular"], "source": "declension"}, {"form": "lhasa apsojeni", "tags": ["genitive", "plural"], "source": "declension"}, {"form": "lhasa apsoani", "tags": ["partitive", "singular"], "source": "declension"}, {"form": "lhasa apsojani", "tags": ["partitive", "plural"], "source": "declension"}, {"form": "lhasa apsossani", "tags": ["inessive", "singular"], "source": "declension"}, {"form": "lhasa apsoissani", "tags": ["inessive", "plural"], "source": "declension"}, {"form": "lhasa apsostani", "tags": ["elative", "singular"], "source": "declension"}, {"form": "lhasa apsoistani", "tags": ["elative", "plural"], "source": "declension"}, {"form": "lhasa apsooni", "tags": ["illative", "singular"], "source": "declension"}, {"form": "lhasa apsoihini", "tags": ["illative", "plural"], "source": "declension"}, {"form": "lhasa apsollani", "tags": ["adessive", "singular"], "source": "declension"}, {"form": "lhasa apsoillani", "tags": ["adessive", "plural"], "source": "declension"}, {"form": "lhasa apsoltani", "tags": ["ablative", "singular"], "source": "declension"}, {"form": "lhasa apsoiltani", "tags": ["ablative", "plural"], "source": "declension"}, {"form": "lhasa apsolleni", "tags": ["allative", "singular"], "source": "declension"}, {"form": "lhasa apsoilleni", "tags": ["allative", "plural"], "source": "declension"}, {"form": "lhasa apsonani", "tags": ["essive", "singular"], "source": "declension"}, {"form": "lhasa apsoinani", "tags": ["essive", "plural"], "source": "declension"}, {"form": "lhasa apsokseni", "tags": ["singular", "translative"], "source": "declension"}, {"form": "lhasa apsoikseni", "tags": ["plural", "translative"], "source": "declension"}, {"form": "-", "tags": ["instructive", "singular"], "source": "declension"}, {"form": "-", "tags": ["instructive", "plural"], "source": "declension"}, {"form": "lhasa apsottani", "tags": ["abessive", "singular"], "source": "declension"}, {"form": "lhasa apsoittani", "tags": ["abessive", "plural"], "source": "declension"}, {"form": "-", "tags": ["comitative", "singular"], "source": "declension"}, {"form": "lhasa apsoineni", "tags": ["comitative", "plural"], "source": "declension"}, {"form": "", "source": "declension", "tags": ["table-tags"]}, {"form": "fi-decl-valo", "source": "declension", "tags": ["inflection-template"]}, {"form": "lhasa apsosi", "tags": ["nominative", "singular"], "source": "declension"}, {"form": "lhasa apsosi", "tags": ["nominative", "plural"], "source": "declension"}, {"form": "lhasa apsosi", "tags": ["accusative", "nominative", "singular"], "source": "declension"}, {"form": "lhasa apsosi", "tags": ["accusative", "nominative", "plural"], "source": "declension"}, {"form": "lhasa apsosi", "tags": ["accusative", "genitive", "singular"], "source": "declension"}, {"form": "lhasa apsosi", "tags": ["accusative", "genitive", "plural"], "source": "declension"}, {"form": "lhasa apsosi", "tags": ["genitive", "singular"], "source": "declension"}, {"form": "lhasa apsojesi", "tags": ["genitive", "plural"], "source": "declension"}, {"form": "lhasa apsoasi", "tags": ["partitive", "singular"], "source": "declension"}, {"form": "lhasa apsojasi", "tags": ["partitive", "plural"], "source": "declension"}, {"form": "lhasa apsossasi", "tags": ["inessive", "singular"], "source": "declension"}, {"form": "lhasa apsoissasi", "tags": ["inessive", "plural"], "source": "declension"}, {"form": "lhasa apsostasi", "tags": ["elative", "singular"], "source": "declension"}, {"form": "lhasa apsoistasi", "tags": ["elative", "plural"], "source": "declension"}, {"form": "lhasa apsoosi", "tags": ["illative", "singular"], "source": "declension"}, {"form": "lhasa apsoihisi", "tags": ["illative", "plural"], "source": "declension"}, {"form": "lhasa apsollasi", "tags": ["adessive", "singular"], "source": "declension"}, {"form": "lhasa apsoillasi", "tags": ["adessive", "plural"], "source": "declension"}, {"form": "lhasa apsoltasi", "tags": ["ablative", "singular"], "source": "declension"}, {"form": "lhasa apsoiltasi", "tags": ["ablative", "plural"], "source": "declension"}, {"form": "lhasa apsollesi", "tags": ["allative", "singular"], "source": "declension"}, {"form": "lhasa apsoillesi", "tags": ["allative", "plural"], "source": "declension"}, {"form": "lhasa apsonasi", "tags": ["essive", "singular"], "source": "declension"}, {"form": "lhasa apsoinasi", "tags": ["essive", "plural"], "source": "declension"}, {"form": "lhasa apsoksesi", "tags": ["singular", "translative"], "source": "declension"}, {"form": "lhasa apsoiksesi", "tags": ["plural", "translative"], "source": "declension"}, {"form": "-", "tags": ["instructive", "singular"], "source": "declension"}, {"form": "-", "tags": ["instructive", "plural"], "source": "declension"}, {"form": "lhasa apsottasi", "tags": ["abessive", "singular"], "source": "declension"}, {"form": "lhasa apsoittasi", "tags": ["abessive", "plural"], "source": "declension"}, {"form": "-", "tags": ["comitative", "singular"], "source": "declension"}, {"form": "lhasa apsoinesi", "tags": ["comitative", "plural"], "source": "declension"}, {"form": "", "source": "declension", "tags": ["table-tags"]}, {"form": "fi-decl-valo", "source": "declension", "tags": ["inflection-template"]}, {"form": "lhasa apsomme", "tags": ["nominative", "singular"], "source": "declension"}, {"form": "lhasa apsomme", "tags": ["nominative", "plural"], "source": "declension"}, {"form": "lhasa apsomme", "tags": ["accusative", "nominative", "singular"], "source": "declension"}, {"form": "lhasa apsomme", "tags": ["accusative", "nominative", "plural"], "source": "declension"}, {"form": "lhasa apsomme", "tags": ["accusative", "genitive", "singular"], "source": "declension"}, {"form": "lhasa apsomme", "tags": ["accusative", "genitive", "plural"], "source": "declension"}, {"form": "lhasa apsomme", "tags": ["genitive", "singular"], "source": "declension"}, {"form": "lhasa apsojemme", "tags": ["genitive", "plural"], "source": "declension"}, {"form": "lhasa apsoamme", "tags": ["partitive", "singular"], "source": "declension"}, {"form": "lhasa apsojamme", "tags": ["partitive", "plural"], "source": "declension"}, {"form": "lhasa apsossamme", "tags": ["inessive", "singular"], "source": "declension"}, {"form": "lhasa apsoissamme", "tags": ["inessive", "plural"], "source": "declension"}, {"form": "lhasa apsostamme", "tags": ["elative", "singular"], "source": "declension"}, {"form": "lhasa apsoistamme", "tags": ["elative", "plural"], "source": "declension"}, {"form": "lhasa apsoomme", "tags": ["illative", "singular"], "source": "declension"}, {"form": "lhasa apsoihimme", "tags": ["illative", "plural"], "source": "declension"}, {"form": "lhasa apsollamme", "tags": ["adessive", "singular"], "source": "declension"}, {"form": "lhasa apsoillamme", "tags": ["adessive", "plural"], "source": "declension"}, {"form": "lhasa apsoltamme", "tags": ["ablative", "singular"], "source": "declension"}, {"form": "lhasa apsoiltamme", "tags": ["ablative", "plural"], "source": "declension"}, {"form": "lhasa apsollemme", "tags": ["allative", "singular"], "source": "declension"}, {"form": "lhasa apsoillemme", "tags": ["allative", "plural"], "source": "declension"}, {"form": "lhasa apsonamme", "tags": ["essive", "singular"], "source": "declension"}, {"form": "lhasa apsoinamme", "tags": ["essive", "plural"], "source": "declension"}, {"form": "lhasa apsoksemme", "tags": ["singular", "translative"], "source": "declension"}, {"form": "lhasa apsoiksemme", "tags": ["plural", "translative"], "source": "declension"}, {"form": "-", "tags": ["instructive", "singular"], "source": "declension"}, {"form": "-", "tags": ["instructive", "plural"], "source": "declension"}, {"form": "lhasa apsottamme", "tags": ["abessive", "singular"], "source": "declension"}, {"form": "lhasa apsoittamme", "tags": ["abessive", "plural"], "source": "declension"}, {"form": "-", "tags": ["comitative", "singular"], "source": "declension"}, {"form": "lhasa apsoinemme", "tags": ["comitative", "plural"], "source": "declension"}, {"form": "", "source": "declension", "tags": ["table-tags"]}, {"form": "fi-decl-valo", "source": "declension", "tags": ["inflection-template"]}, {"form": "lhasa apsonne", "tags": ["nominative", "singular"], "source": "declension"}, {"form": "lhasa apsonne", "tags": ["nominative", "plural"], "source": "declension"}, {"form": "lhasa apsonne", "tags": ["accusative", "nominative", "singular"], "source": "declension"}, {"form": "lhasa apsonne", "tags": ["accusative", "nominative", "plural"], "source": "declension"}, {"form": "lhasa apsonne", "tags": ["accusative", "genitive", "singular"], "source": "declension"}, {"form": "lhasa apsonne", "tags": ["accusative", "genitive", "plural"], "source": "declension"}, {"form": "lhasa apsonne", "tags": ["genitive", "singular"], "source": "declension"}, {"form": "lhasa apsojenne", "tags": ["genitive", "plural"], "source": "declension"}, {"form": "lhasa apsoanne", "tags": ["partitive", "singular"], "source": "declension"}, {"form": "lhasa apsojanne", "tags": ["partitive", "plural"], "source": "declension"}, {"form": "lhasa apsossanne", "tags": ["inessive", "singular"], "source": "declension"}, {"form": "lhasa apsoissanne", "tags": ["inessive", "plural"], "source": "declension"}, {"form": "lhasa apsostanne", "tags": ["elative", "singular"], "source": "declension"}, {"form": "lhasa apsoistanne", "tags": ["elative", "plural"], "source": "declension"}, {"form": "lhasa apsoonne", "tags": ["illative", "singular"], "source": "declension"}, {"form": "lhasa apsoihinne", "tags": ["illative", "plural"], "source": "declension"}, {"form": "lhasa apsollanne", "tags": ["adessive", "singular"], "source": "declension"}, {"form": "lhasa apsoillanne", "tags": ["adessive", "plural"], "source": "declension"}, {"form": "lhasa apsoltanne", "tags": ["ablative", "singular"], "source": "declension"}, {"form": "lhasa apsoiltanne", "tags": ["ablative", "plural"], "source": "declension"}, {"form": "lhasa apsollenne", "tags": ["allative", "singular"], "source": "declension"}, {"form": "lhasa apsoillenne", "tags": ["allative", "plural"], "source": "declension"}, {"form": "lhasa apsonanne", "tags": ["essive", "singular"], "source": "declension"}, {"form": "lhasa apsoinanne", "tags": ["essive", "plural"], "source": "declension"}, {"form": "lhasa apsoksenne", "tags": ["singular", "translative"], "source": "declension"}, {"form": "lhasa apsoiksenne", "tags": ["plural", "translative"], "source": "declension"}, {"form": "-", "tags": ["instructive", "singular"], "source": "declension"}, {"form": "-", "tags": ["instructive", "plural"], "source": "declension"}, {"form": "lhasa apsottanne", "tags": ["abessive", "singular"], "source": "declension"}, {"form": "lhasa apsoittanne", "tags": ["abessive", "plural"], "source": "declension"}, {"form": "-", "tags": ["comitative", "singular"], "source": "declension"}, {"form": "lhasa apsoinenne", "tags": ["comitative", "plural"], "source": "declension"}, {"form": "", "source": "declension", "tags": ["table-tags"]}, {"form": "fi-decl-valo", "source": "declension", "tags": ["inflection-template"]}, {"form": "lhasa apsonsa", "tags": ["nominative", "singular"], "source": "declension"}, {"form": "lhasa apsonsa", "tags": ["nominative", "plural"], "source": "declension"}, {"form": "lhasa apsonsa", "tags": ["accusative", "nominative", "singular"], "source": "declension"}, {"form": "lhasa apsonsa", "tags": ["accusative", "nominative", "plural"], "source": "declension"}, {"form": "lhasa apsonsa", "tags": ["accusative", "genitive", "singular"], "source": "declension"}, {"form": "lhasa apsonsa", "tags": ["accusative", "genitive", "plural"], "source": "declension"}, {"form": "lhasa apsonsa", "tags": ["genitive", "singular"], "source": "declension"}, {"form": "lhasa apsojensa", "tags": ["genitive", "plural"], "source": "declension"}, {"form": "lhasa apsoaan", "tags": ["partitive", "singular"], "source": "declension"}, {"form": "lhasa apsoansa", "tags": ["partitive", "singular"], "source": "declension"}, {"form": "lhasa apsojaan", "tags": ["partitive", "plural"], "source": "declension"}, {"form": "lhasa apsojansa", "tags": ["partitive", "plural"], "source": "declension"}, {"form": "lhasa apsossaan", "tags": ["inessive", "singular"], "source": "declension"}, {"form": "lhasa apsossansa", "tags": ["inessive", "singular"], "source": "declension"}, {"form": "lhasa apsoissaan", "tags": ["inessive", "plural"], "source": "declension"}, {"form": "lhasa apsoissansa", "tags": ["inessive", "plural"], "source": "declension"}, {"form": "lhasa apsostaan", "tags": ["elative", "singular"], "source": "declension"}, {"form": "lhasa apsostansa", "tags": ["elative", "singular"], "source": "declension"}, {"form": "lhasa apsoistaan", "tags": ["elative", "plural"], "source": "declension"}, {"form": "lhasa apsoistansa", "tags": ["elative", "plural"], "source": "declension"}, {"form": "lhasa apsoonsa", "tags": ["illative", "singular"], "source": "declension"}, {"form": "lhasa apsoihinsa", "tags": ["illative", "plural"], "source": "declension"}, {"form": "lhasa apsollaan", "tags": ["adessive", "singular"], "source": "declension"}, {"form": "lhasa apsollansa", "tags": ["adessive", "singular"], "source": "declension"}, {"form": "lhasa apsoillaan", "tags": ["adessive", "plural"], "source": "declension"}, {"form": "lhasa apsoillansa", "tags": ["adessive", "plural"], "source": "declension"}, {"form": "lhasa apsoltaan", "tags": ["ablative", "singular"], "source": "declension"}, {"form": "lhasa apsoltansa", "tags": ["ablative", "singular"], "source": "declension"}, {"form": "lhasa apsoiltaan", "tags": ["ablative", "plural"], "source": "declension"}, {"form": "lhasa apsoiltansa", "tags": ["ablative", "plural"], "source": "declension"}, {"form": "lhasa apsolleen", "tags": ["allative", "singular"], "source": "declension"}, {"form": "lhasa apsollensa", "tags": ["allative", "singular"], "source": "declension"}, {"form": "lhasa apsoilleen", "tags": ["allative", "plural"], "source": "declension"}, {"form": "lhasa apsoillensa", "tags": ["allative", "plural"], "source": "declension"}, {"form": "lhasa apsonaan", "tags": ["essive", "singular"], "source": "declension"}, {"form": "lhasa apsonansa", "tags": ["essive", "singular"], "source": "declension"}, {"form": "lhasa apsoinaan", "tags": ["essive", "plural"], "source": "declension"}, {"form": "lhasa apsoinansa", "tags": ["essive", "plural"], "source": "declension"}, {"form": "lhasa apsokseen", "tags": ["singular", "translative"], "source": "declension"}, {"form": "lhasa apsoksensa", "tags": ["singular", "translative"], "source": "declension"}, {"form": "lhasa apsoikseen", "tags": ["plural", "translative"], "source": "declension"}, {"form": "lhasa apsoiksensa", "tags": ["plural", "translative"], "source": "declension"}, {"form": "-", "tags": ["instructive", "singular"], "source": "declension"}, {"form": "-", "tags": ["instructive", "plural"], "source": "declension"}, {"form": "lhasa apsottaan", "tags": ["abessive", "singular"], "source": "declension"}, {"form": "lhasa apsottansa", "tags": ["abessive", "singular"], "source": "declension"}, {"form": "lhasa apsoittaan", "tags": ["abessive", "plural"], "source": "declension"}, {"form": "lhasa apsoittansa", "tags": ["abessive", "plural"], "source": "declension"}, {"form": "-", "tags": ["comitative", "singular"], "source": "declension"}, {"form": "lhasa apsoineen", "tags": ["comitative", "plural"], "source": "declension"}, {"form": "lhasa apsoinensa", "tags": ["comitative", "plural"], "source": "declension"}], "word": "lhasa apso", "lang": "Finnish", "lang_code": "fi"}
]}
